pyhtml2pdf/__init__.py
pyhtml2pdf/compressor.py
pyhtml2pdf/converter.py
pyhtml2pdf/utils.py
pyhtml2pdf-0.1.0.dist-info/licenses/LICENSE
pyhtml2pdf-0.1.0.dist-info/METADATA
pyhtml2pdf-0.1.0.dist-info/WHEEL
pyhtml2pdf-0.1.0.dist-info/top_level.txt
pyhtml2pdf-0.1.0.dist-info/RECORD
