Metadata-Version: 2.4
Name: pyhtml2pdf
Version: 0.1.0
Summary: Simple python wrapper to convert HTML to PDF with headless Chrome via selenium.
Home-page: https://github.com/kumaF/pyhtml2pdf
Author: Kumara Fernando
Author-email: mklmfernando@gmail.com
Classifier: Programming Language :: Python :: 3
Classifier: License :: OSI Approved :: MIT License
Classifier: Operating System :: OS Independent
Requires-Python: >=3.10
License-File: LICENSE
Requires-Dist: selenium
Requires-Dist: webdriver-manager
Requires-Dist: pikepdf
Dynamic: author
Dynamic: author-email
Dynamic: classifier
Dynamic: description
Dynamic: description-content-type
Dynamic: home-page
Dynamic: license-file
Dynamic: requires-dist
Dynamic: requires-python
Dynamic: summary
